{
    "AX": {
        "error": 0.004711963869955644,
        "filter_outliers_dict": {
            "filter_outliers": true,
            "iterations": 1,
            "std_devs": 2
        },
        "fit": "Average",
        "fn": 117,
        "include_baseline_error": false,
        "n": 120,
        "reviewed": true,
        "value": 0.02750134148744918
    },
    "CDD": {
        "error": 1.31610132444103e-05,
        "filter_outliers_dict": {
            "filter_outliers": true,
            "iterations": 1,
            "std_devs": 10
        },
        "fit": "Average",
        "fn": 120,
        "include_baseline_error": false,
        "n": 120,
        "reviewed": true,
        "value": 0.00015425657693413086
    },
    "H1": {
        "error": 0.0034647170119054957,
        "filter_outliers_dict": {
            "filter_outliers": true,
            "iterations": 1,
            "std_devs": 2
        },
        "fit": "Average",
        "fn": 114,
        "include_baseline_error": false,
        "n": 120,
        "reviewed": true,
        "value": 0.19902985477656648
    },
    "H2": {
        "error": 0.0050589350422038295,
        "filter_outliers_dict": {
            "filter_outliers": true,
            "iterations": 1,
            "std_devs": 2
        },
        "fit": "average",
        "value": 0.07797703656379591
    },
    "L1": {
        "error": 0.0018927943708733853,
        "filter_outliers_dict": {
            "filter_outliers": true,
            "iterations": 1,
            "std_devs": 2
        },
        "fit": "Average",
        "fn": 114,
        "include_baseline_error": false,
        "n": 120,
        "reviewed": true,
        "value": -0.17669864417168132
    },
    "L2": {
        "error": 0.004312935392356169,
        "filter_outliers_dict": {
            "filter_outliers": true,
            "iterations": 1,
            "std_devs": 2
        },
        "fit": "Average",
        "fn": 115,
        "include_baseline_error": false,
        "n": 120,
        "reviewed": true,
        "value": -0.022763208079192302
    }
}