{
    "Ar36": {
        "error": 0.000718917838423262, 
        "filter_outliers_dict": {
            "filter_outliers": true, 
            "iterations": 1, 
            "std_devs": 2
        }, 
        "fit": "Parabolic", 
        "value": 0.18135846122988947
    }, 
    "Ar37": {
        "error": 0.0051662605741553055, 
        "filter_outliers_dict": {
            "filter_outliers": true, 
            "iterations": 1, 
            "std_devs": 2
        }, 
        "fit": "linear", 
        "value": 0.14852374634931936
    }, 
    "Ar38": {
        "error": 0.0020248689758903538, 
        "filter_outliers_dict": {
            "filter_outliers": true, 
            "iterations": 1, 
            "std_devs": 2
        }, 
        "fit": "linear", 
        "value": 0.03664497976803949
    }, 
    "Ar39": {
        "error": 0.00859807363106813, 
        "filter_outliers_dict": {
            "filter_outliers": true, 
            "iterations": 1, 
            "std_devs": 2
        }, 
        "fit": "Parabolic", 
        "value": 0.06048552034403356
    }, 
    "Ar40": {
        "error": 0.010950888926321813, 
        "filter_outliers_dict": {
            "filter_outliers": true, 
            "iterations": 1, 
            "std_devs": 2
        }, 
        "fit": "Parabolic", 
        "value": 54.32523806271534
    }, 
    "Ar41": {
        "error": 0.005258507398237516, 
        "filter_outliers_dict": {
            "filter_outliers": true, 
            "iterations": 1, 
            "std_devs": 2
        }, 
        "fit": "linear", 
        "value": 0.07553919965436573
    }
}