{
    "Ar36": {
        "error": 0.0030950155018141315, 
        "filter_outliers_dict": {
            "filter_outliers": true, 
            "iterations": 1, 
            "std_devs": 2
        }, 
        "fit": "Parabolic", 
        "value": 3.1090146464203112
    }, 
    "Ar37": {
        "error": 0.0051713692705222395, 
        "filter_outliers_dict": {
            "filter_outliers": true, 
            "iterations": 1, 
            "std_devs": 2
        }, 
        "fit": "linear", 
        "value": 0.008771017345448466
    }, 
    "Ar38": {
        "error": 0.0019590399874133122, 
        "filter_outliers_dict": {
            "filter_outliers": true, 
            "iterations": 1, 
            "std_devs": 2
        }, 
        "fit": "linear", 
        "value": 0.41806607043389277
    }, 
    "Ar39": {
        "error": 0.008070144387232603, 
        "filter_outliers_dict": {
            "filter_outliers": true, 
            "iterations": 1, 
            "std_devs": 2
        }, 
        "fit": "Parabolic", 
        "value": 0.16338106896640325
    }, 
    "Ar40": {
        "error": 0.04339990083088701, 
        "filter_outliers_dict": {
            "filter_outliers": true, 
            "iterations": 1, 
            "std_devs": 2
        }, 
        "fit": "Parabolic", 
        "value": 899.6967629260917
    }, 
    "Ar41": {
        "error": 0.005082350212464871, 
        "filter_outliers_dict": {
            "filter_outliers": true, 
            "iterations": 1, 
            "std_devs": 2
        }, 
        "fit": "linear", 
        "value": 0.1953912912440348
    }
}