{
    "Ar36": {
        "error": 0.00092047538583409, 
        "filter_outliers_dict": {
            "filter_outliers": true, 
            "iterations": 1, 
            "std_devs": 2
        }, 
        "fit": "Parabolic", 
        "value": 0.32066680397664643
    }, 
    "Ar37": {
        "error": 0.005248851193896905, 
        "filter_outliers_dict": {
            "filter_outliers": true, 
            "iterations": 1, 
            "std_devs": 2
        }, 
        "fit": "linear", 
        "value": 0.005765435645062513
    }, 
    "Ar38": {
        "error": 0.0021879998432721005, 
        "filter_outliers_dict": {
            "filter_outliers": true, 
            "iterations": 1, 
            "std_devs": 2
        }, 
        "fit": "linear", 
        "value": 0.044191115844999365
    }, 
    "Ar39": {
        "error": 0.008126731415756887, 
        "filter_outliers_dict": {
            "filter_outliers": true, 
            "iterations": 1, 
            "std_devs": 2
        }, 
        "fit": "Parabolic", 
        "value": -0.018134752771035316
    }, 
    "Ar40": {
        "error": 0.012244306041595003, 
        "filter_outliers_dict": {
            "filter_outliers": true, 
            "iterations": 1, 
            "std_devs": 2
        }, 
        "fit": "Parabolic", 
        "value": 92.92659776693802
    }, 
    "Ar41": {
        "error": 0.006043962879495824, 
        "filter_outliers_dict": {
            "filter_outliers": true, 
            "iterations": 1, 
            "std_devs": 2
        }, 
        "fit": "linear", 
        "value": -0.15476436155821752
    }
}