{
    "Ar36": {
        "error": 0.006047617527495715, 
        "filter_outliers_dict": {
            "filter_outliers": true, 
            "iterations": 1, 
            "std_devs": 2
        }, 
        "fit": "Parabolic", 
        "value": 9.065201014108629
    }, 
    "Ar37": {
        "error": 0.005168803982335175, 
        "filter_outliers_dict": {
            "filter_outliers": true, 
            "iterations": 1, 
            "std_devs": 2
        }, 
        "fit": "linear", 
        "value": 0.014759659303733762
    }, 
    "Ar38": {
        "error": 0.0024913842364563945, 
        "filter_outliers_dict": {
            "filter_outliers": true, 
            "iterations": 1, 
            "std_devs": 2
        }, 
        "fit": "linear", 
        "value": 1.6983082340646503
    }, 
    "Ar39": {
        "error": 0.010202906357145046, 
        "filter_outliers_dict": {
            "filter_outliers": true, 
            "iterations": 1, 
            "std_devs": 2
        }, 
        "fit": "Parabolic", 
        "value": -0.031715836150989614
    }, 
    "Ar40": {
        "error": 0.07507309994957098, 
        "filter_outliers_dict": {
            "filter_outliers": true, 
            "iterations": 1, 
            "std_devs": 2
        }, 
        "fit": "Parabolic", 
        "value": 2667.5971387594905
    }, 
    "Ar41": {
        "error": 0.0058796077666019055, 
        "filter_outliers_dict": {
            "filter_outliers": true, 
            "iterations": 1, 
            "std_devs": 2
        }, 
        "fit": "linear", 
        "value": -0.028225501978121407
    }
}