{
    "Ar36": {
        "error": 0.00020559790949751066, 
        "fit": "previous", 
        "references": [
            {
                "exclude": false, 
                "record_id": "ba-01-J-2081"
            }
        ], 
        "value": 0.006931883338253831
    }, 
    "Ar37": {
        "error": 0.0049085426009007425, 
        "fit": "previous", 
        "references": [
            {
                "exclude": false, 
                "record_id": "ba-01-J-2081"
            }
        ], 
        "value": 0.026148661672649065
    }, 
    "Ar38": {
        "error": 0.0021105202440778043, 
        "fit": "previous", 
        "references": [
            {
                "exclude": false, 
                "record_id": "ba-01-J-2081"
            }
        ], 
        "value": 0.015114822137640607
    }, 
    "Ar39": {
        "error": 0.008960221002809162, 
        "fit": "previous", 
        "references": [
            {
                "exclude": false, 
                "record_id": "ba-01-J-2081"
            }
        ], 
        "value": 0.06172892900939301
    }, 
    "Ar40": {
        "error": 0.0067042566551808475, 
        "fit": "previous", 
        "references": [
            {
                "exclude": false, 
                "record_id": "ba-01-J-2081"
            }
        ], 
        "value": 0.14126766913369823
    }, 
    "Ar41": {
        "error": 0.005578490887443818, 
        "fit": "previous", 
        "references": [
            {
                "exclude": false, 
                "record_id": "ba-01-J-2081"
            }
        ], 
        "value": 0.0459129593552057
    }
}